flask_mail_template_tester.py
flask_mail_template_tester-0.3.1.dist-info/AUTHORS
flask_mail_template_tester-0.3.1.dist-info/METADATA
flask_mail_template_tester-0.3.1.dist-info/WHEEL
flask_mail_template_tester-0.3.1.dist-info/entry_points.txt
flask_mail_template_tester-0.3.1.dist-info/top_level.txt
flask_mail_template_tester-0.3.1.dist-info/RECORD
