Metadata-Version: 2.1
Name: flask-mail-template-tester
Version: 0.3.1
Summary: Add ``flask template-test`` command to send template emails with data read from a test file.
Home-page: https://github.com/geodav-tech/flask-mail-template-tester
Author: Shawn Pacarar
Author-email: shawn@geodav.tech
License: MIT
Platform: any
Classifier: Development Status :: 3 - Alpha
Classifier: Environment :: Console
Classifier: Intended Audience :: Developers
Classifier: License :: OSI Approved :: MIT License
Classifier: Operating System :: OS Independent
Classifier: Programming Language :: Python :: 3
Classifier: Programming Language :: Python :: 3.6
Classifier: Programming Language :: Python :: 3.7
Classifier: Programming Language :: Python :: 3.8
Classifier: Programming Language :: Python :: 3.9
Classifier: Programming Language :: Python :: 3.10
Classifier: Programming Language :: Python
Requires-Dist: Flask (>=0.12.2)
Requires-Dist: click (>=6.7)
